signalspam.py
signal_spam-0.2.dist-info/LICENSE
signal_spam-0.2.dist-info/METADATA
signal_spam-0.2.dist-info/WHEEL
signal_spam-0.2.dist-info/entry_points.txt
signal_spam-0.2.dist-info/top_level.txt
signal_spam-0.2.dist-info/RECORD
