Metadata-Version: 2.1
Name: signal-spam
Version: 0.2
Summary: Report an eml file to signal-spam.fr
Author-email: Julien Palard <julien@palard.fr>
License: MIT License
Project-URL: homepage, https://git.afpy.org/mdk/signal-spam
Requires-Python: >=3.7
License-File: LICENSE
Requires-Dist: requests
